osu_sr_calculator/BeatmapParser.py
osu_sr_calculator/DifficultyHitObjectCreator.py
osu_sr_calculator/Logger.py
osu_sr_calculator/OsuService.py
osu_sr_calculator/PathApproximator.py
osu_sr_calculator/Precision.py
osu_sr_calculator/SliderPath.py
osu_sr_calculator/StarRatingCalculator.py
osu_sr_calculator/__init__.py
osu_sr_calculator/main.py
osu_sr_calculator/Objects/Vector2.py
osu_sr_calculator/Objects/__init__.py
osu_sr_calculator/Objects/osu/Beatmap.py
osu_sr_calculator/Objects/osu/HitType.py
osu_sr_calculator/Objects/osu/PathType.py
osu_sr_calculator/Objects/osu/__init__.py
osu_sr_calculator/Objects/osu/HitObjects/DifficultyHitObject.py
osu_sr_calculator/Objects/osu/HitObjects/HitCircle.py
osu_sr_calculator/Objects/osu/HitObjects/HitObject.py
osu_sr_calculator/Objects/osu/HitObjects/Slider.py
osu_sr_calculator/Objects/osu/HitObjects/Spinner.py
osu_sr_calculator/Objects/osu/HitObjects/__init__.py
osu_sr_calculator/Objects/osu/HitObjects/SliderObjects/HeadCircle.py
osu_sr_calculator/Objects/osu/HitObjects/SliderObjects/RepeatPoint.py
osu_sr_calculator/Objects/osu/HitObjects/SliderObjects/SliderTick.py
osu_sr_calculator/Objects/osu/HitObjects/SliderObjects/TailCircle.py
osu_sr_calculator/Objects/osu/HitObjects/SliderObjects/__init__.py
osu_sr_calculator/Skills/Aim.py
osu_sr_calculator/Skills/OsuStrainSkill.py
osu_sr_calculator/Skills/Skill.py
osu_sr_calculator/Skills/Speed.py
osu_sr_calculator/Skills/__init__.py
osu_sr_calculator-1.1.0.dist-info/LICENSE
osu_sr_calculator-1.1.0.dist-info/METADATA
osu_sr_calculator-1.1.0.dist-info/WHEEL
osu_sr_calculator-1.1.0.dist-info/top_level.txt
osu_sr_calculator-1.1.0.dist-info/RECORD
