Metadata-Version: 2.1
Name: osu-sr-calculator
Version: 1.1.0
Summary: MrHelix's osu! star rating calculator rewritten for your Python needs
Home-page: https://github.com/Piggey/osu_sr_calculator
Author: Piggey
License: UNKNOWN
Keywords: osu!,osu,star rating,calculator,sr
Platform: UNKNOWN
Classifier: Development Status :: 3 - Alpha
Classifier: Natural Language :: English
Classifier: Intended Audience :: Developers
Classifier: Operating System :: OS Independent
Classifier: Programming Language :: Python :: 3
Requires-Python: >=3.7
Requires-Dist: requests (==2.25.1)
